{
	"info": {
		"_postman_id": "ae61e688-c698-4937-8f6b-1774d8b7c6eb",
		"name": "car sharing",
		"schema": "https://schema.getpostman.com/json/collection/v2.1.0/collection.json",
		"_exporter_id": "39735772"
	},
	"item": [
		{
			"name": "authorizaton",
			"item": [
				{
					"name": "login admin",
					"request": {
						"auth": {
							"type": "noauth"
						},
						"method": "POST",
						"header": [],
						"body": {
							"mode": "raw",
							"raw": "{\r\n    \"email\":\"admin@example.com\",\r\n    \"password\":\"admin\"\r\n}",
							"options": {
								"raw": {
									"language": "json"
								}
							}
						},
						"url": {
							"raw": "http://localhost:8080/auth/login",
							"protocol": "http",
							"host": [
								"localhost"
							],
							"port": "8080",
							"path": [
								"auth",
								"login"
							]
						}
					},
					"response": []
				},
				{
					"name": "login user",
					"request": {
						"auth": {
							"type": "noauth"
						},
						"method": "POST",
						"header": [],
						"body": {
							"mode": "raw",
							"raw": "{\r\n    \"email\":\"user@example.com\",\r\n    \"password\":\"user\"\r\n}",
							"options": {
								"raw": {
									"language": "json"
								}
							}
						},
						"url": {
							"raw": "http://localhost:8080/auth/login",
							"protocol": "http",
							"host": [
								"localhost"
							],
							"port": "8080",
							"path": [
								"auth",
								"login"
							]
						}
					},
					"response": []
				},
				{
					"name": "create user",
					"request": {
						"auth": {
							"type": "noauth"
						},
						"method": "POST",
						"header": [],
						"body": {
							"mode": "raw",
							"raw": "{\r\n    \"email\":\"\",\r\n    \"password\":\"\",\r\n    \"repeatPassword\":\"\",\r\n    \"firstName\":\"\",\r\n    \"lastName\":\"\"\r\n}",
							"options": {
								"raw": {
									"language": "json"
								}
							}
						},
						"url": {
							"raw": "http://localhost:8080/auth/register",
							"protocol": "http",
							"host": [
								"localhost"
							],
							"port": "8080",
							"path": [
								"auth",
								"register"
							]
						}
					},
					"response": []
				}
			]
		},
		{
			"name": "car",
			"item": [
				{
					"name": "get all cars",
					"request": {
						"auth": {
							"type": "noauth"
						},
						"method": "GET",
						"header": [],
						"url": {
							"raw": "http://localhost:8080/cars",
							"protocol": "http",
							"host": [
								"localhost"
							],
							"port": "8080",
							"path": [
								"cars"
							]
						}
					},
					"response": []
				},
				{
					"name": "get car by id",
					"request": {
						"auth": {
							"type": "noauth"
						},
						"method": "GET",
						"header": [],
						"url": {
							"raw": "http://localhost:8080/cars/",
							"protocol": "http",
							"host": [
								"localhost"
							],
							"port": "8080",
							"path": [
								"cars",
								""
							]
						}
					},
					"response": []
				},
				{
					"name": "create car",
					"request": {
						"auth": {
							"type": "bearer",
							"bearer": [
								{
									"key": "token",
									"value": "eyJhbGciOiJIUzUxMiJ9.eyJzdWIiOiJhZG1pbkBleGFtcGxlLmNvbSIsInJvbGVzIjpbIlVTRVIiLCJBRE1JTiJdLCJpYXQiOjE3Mzc3MjExMTEsImV4cCI6MTc2NzcyMTExMX0.Tvo2MEOgVyb74y_8X_Y93v1DYn4n6-QF9gn7TMt4vZy9QJ6x1ejQ6JRh-CSjac7nrO3xnpeU1LHmW0b_t86MaQ",
									"type": "string"
								}
							]
						},
						"method": "POST",
						"header": [],
						"body": {
							"mode": "raw",
							"raw": "{\r\n    \"model\": \"Q8\",\r\n    \"brand\": \"Audi\",\r\n    \"inventory\": 6,\r\n    \"dailyFee\": 550,\r\n    \"type\": \"UNIVERSAL\"\r\n}",
							"options": {
								"raw": {
									"language": "json"
								}
							}
						},
						"url": {
							"raw": "http://localhost:8080/cars",
							"protocol": "http",
							"host": [
								"localhost"
							],
							"port": "8080",
							"path": [
								"cars"
							]
						}
					},
					"response": []
				},
				{
					"name": "update car",
					"request": {
						"auth": {
							"type": "bearer",
							"bearer": [
								{
									"key": "token",
									"value": "eyJhbGciOiJIUzUxMiJ9.eyJzdWIiOiJhZG1pbkBleGFtcGxlLmNvbSIsInJvbGVzIjpbIlVTRVIiLCJBRE1JTiJdLCJpYXQiOjE3MzcwNDY3NjQsImV4cCI6MTc2NzA0Njc2NH0.BABqKezPDvISckH5goF-hV9xSbYVK_0yheqaoqIISTbJh_s8qeXcR5gVTS8dw3KXRh3T2X9VE9-AgPumuRd78g",
									"type": "string"
								}
							]
						},
						"method": "PUT",
						"header": [],
						"body": {
							"mode": "raw",
							"raw": "{\r\n    \"model\": \"Q8\",\r\n    \"brand\": \"Audi\",\r\n    \"inventory\": 6,\r\n    \"dailyFee\": 550,\r\n    \"type\": \"UNIVERSAL\"\r\n}",
							"options": {
								"raw": {
									"language": "json"
								}
							}
						},
						"url": {
							"raw": "http://localhost:8080/cars/1",
							"protocol": "http",
							"host": [
								"localhost"
							],
							"port": "8080",
							"path": [
								"cars",
								"1"
							]
						}
					},
					"response": []
				},
				{
					"name": "delete car",
					"request": {
						"auth": {
							"type": "bearer",
							"bearer": [
								{
									"key": "token",
									"value": "eyJhbGciOiJIUzUxMiJ9.eyJzdWIiOiJhZG1pbkBleGFtcGxlLmNvbSIsInJvbGVzIjpbIlVTRVIiLCJBRE1JTiJdLCJpYXQiOjE3MzcwNDY3NjQsImV4cCI6MTc2NzA0Njc2NH0.BABqKezPDvISckH5goF-hV9xSbYVK_0yheqaoqIISTbJh_s8qeXcR5gVTS8dw3KXRh3T2X9VE9-AgPumuRd78g",
									"type": "string"
								}
							]
						},
						"method": "DELETE",
						"header": [],
						"url": {
							"raw": "http://localhost:8080/cars/1",
							"protocol": "http",
							"host": [
								"localhost"
							],
							"port": "8080",
							"path": [
								"cars",
								"1"
							]
						}
					},
					"response": []
				}
			]
		},
		{
			"name": "user",
			"item": [
				{
					"name": "update profile info",
					"request": {
						"auth": {
							"type": "bearer",
							"bearer": [
								{
									"key": "token",
									"value": "eyJhbGciOiJIUzUxMiJ9.eyJzdWIiOiJ0ZXN0QG1haWwuY29tIiwicm9sZXMiOlsiVVNFUiJdLCJpYXQiOjE3MzY3OTIyMDcsImV4cCI6MTc2Njc5MjIwN30.ZmzO-F4IIlODoDBEl7Hbn-R3hi4CrarPuK5ZQQcF7q4B1khQMLjVsbZCaXXOp4Z0v3LXNUsOLpMDR7iHAn4T7A",
									"type": "string"
								}
							]
						},
						"method": "PUT",
						"header": [],
						"body": {
							"mode": "raw",
							"raw": "{\r\n    \"email\":\"test@mail.com\",\r\n    \"password\":\"12345\",\r\n    \"repeatPassword\":\"12345\",\r\n    \"firstName\":\"test\",\r\n    \"lastName\":\"test\"\r\n}",
							"options": {
								"raw": {
									"language": "json"
								}
							}
						},
						"url": {
							"raw": "http://localhost:8080/users",
							"protocol": "http",
							"host": [
								"localhost"
							],
							"port": "8080",
							"path": [
								"users"
							]
						}
					},
					"response": []
				},
				{
					"name": "update user's roles",
					"request": {
						"auth": {
							"type": "bearer",
							"bearer": [
								{
									"key": "token",
									"value": "eyJhbGciOiJIUzUxMiJ9.eyJzdWIiOiJhZG1pbkBleGFtcGxlLmNvbSIsInJvbGVzIjpbIkFETUlOIiwiVVNFUiJdLCJpYXQiOjE3MzY4NjE1NjMsImV4cCI6MTc2Njg2MTU2M30.dGZ-gfNWz8zriv4tdKEDOuDldeRGN_9AyUHXx0FmEfNITo5VjPVZ7-HMuEN2p7f-tpM_3aNTK56kr25uugtGXw",
									"type": "string"
								}
							]
						},
						"method": "PUT",
						"header": [],
						"body": {
							"mode": "raw",
							"raw": "{\r\n    \"rolesIds\":[]\r\n}",
							"options": {
								"raw": {
									"language": "json"
								}
							}
						},
						"url": {
							"raw": "http://localhost:8080/2",
							"protocol": "http",
							"host": [
								"localhost"
							],
							"port": "8080",
							"path": [
								"2"
							]
						}
					},
					"response": []
				},
				{
					"name": "get my profile info",
					"request": {
						"auth": {
							"type": "bearer",
							"bearer": [
								{
									"key": "token",
									"value": "eyJhbGciOiJIUzUxMiJ9.eyJzdWIiOiJ1c2VyQGV4YW1wbGUuY29tIiwicm9sZXMiOlsiVVNFUiJdLCJpYXQiOjE3MzcwNDQzMjksImV4cCI6MTc2NzA0NDMyOX0.Wybe0ZtsPiwiMpAEf6qpQgeUEhCP_ympGhbptZZPiWCNxdXYiIdMS-EyGuLHmPE_86WiqfAlFk-cSrEDHPWvOQ",
									"type": "string"
								}
							]
						},
						"method": "GET",
						"header": [],
						"url": {
							"raw": "http://localhost:8080/users",
							"protocol": "http",
							"host": [
								"localhost"
							],
							"port": "8080",
							"path": [
								"users"
							]
						}
					},
					"response": []
				}
			]
		},
		{
			"name": "rental",
			"item": [
				{
					"name": "rent a car",
					"request": {
						"auth": {
							"type": "bearer",
							"bearer": [
								{
									"key": "token",
									"value": "eyJhbGciOiJIUzUxMiJ9.eyJzdWIiOiJ1c2VyQGV4YW1wbGUuY29tIiwicm9sZXMiOlsiVVNFUiJdLCJpYXQiOjE3Mzg1OTIxNDUsImV4cCI6MTczODYyMjE0NX0.-sqGlSuSu1oDhsXocOPG4Ysma8tUY7yIaqC7PB7oCZu03saUAVREPXl_DBYoct3rZ3-9smIVDV59y1J_Vz_F_w",
									"type": "string"
								}
							]
						},
						"method": "POST",
						"header": [],
						"body": {
							"mode": "raw",
							"raw": "{\r\n    \"rentalDate\":\"2025-02-03\",\r\n    \"returnDate\":\"2025-04-01\",\r\n    \"carId\":\"1\"\r\n}",
							"options": {
								"raw": {
									"language": "json"
								}
							}
						},
						"url": {
							"raw": "http://localhost:8080/rentals",
							"protocol": "http",
							"host": [
								"localhost"
							],
							"port": "8080",
							"path": [
								"rentals"
							]
						}
					},
					"response": []
				},
				{
					"name": "close rental",
					"request": {
						"auth": {
							"type": "bearer",
							"bearer": [
								{
									"key": "token",
									"value": "eyJhbGciOiJIUzUxMiJ9.eyJzdWIiOiJ1c2VyQGV4YW1wbGUuY29tIiwicm9sZXMiOlsiVVNFUiJdLCJpYXQiOjE3MzcwNDQzMjksImV4cCI6MTc2NzA0NDMyOX0.Wybe0ZtsPiwiMpAEf6qpQgeUEhCP_ympGhbptZZPiWCNxdXYiIdMS-EyGuLHmPE_86WiqfAlFk-cSrEDHPWvOQ",
									"type": "string"
								}
							]
						},
						"method": "POST",
						"header": [],
						"body": {
							"mode": "raw",
							"raw": "{\r\n    \"actualReturnDate\":\"23.01.2025\"\r\n}",
							"options": {
								"raw": {
									"language": "json"
								}
							}
						},
						"url": {
							"raw": "http://localhost:8080/rentals/1",
							"protocol": "http",
							"host": [
								"localhost"
							],
							"port": "8080",
							"path": [
								"rentals",
								"1"
							]
						}
					},
					"response": []
				},
				{
					"name": "get all rentals",
					"request": {
						"auth": {
							"type": "bearer",
							"bearer": [
								{
									"key": "token",
									"value": "eyJhbGciOiJIUzUxMiJ9.eyJzdWIiOiJ1c2VyQGV4YW1wbGUuY29tIiwicm9sZXMiOlsiVVNFUiJdLCJpYXQiOjE3MzcxMTQyMjMsImV4cCI6MTc2NzExNDIyM30.rAAs-CwZfwMCN5r1xWI2lsPMu4ZXjobkud0XA4BQWditk0ZQFzfFpOM08QcNEXAMS4Kh1NEbwEcuyWKVBZVaxA",
									"type": "string"
								}
							]
						},
						"method": "GET",
						"header": [],
						"url": {
							"raw": "http://localhost:8080/rentals?is_active=false",
							"protocol": "http",
							"host": [
								"localhost"
							],
							"port": "8080",
							"path": [
								"rentals"
							],
							"query": [
								{
									"key": "is_active",
									"value": "false"
								}
							]
						}
					},
					"response": []
				},
				{
					"name": "get all active rentals",
					"request": {
						"auth": {
							"type": "bearer",
							"bearer": [
								{
									"key": "token",
									"value": "eyJhbGciOiJIUzUxMiJ9.eyJzdWIiOiJhZG1pbkBleGFtcGxlLmNvbSIsInJvbGVzIjpbIlVTRVIiLCJBRE1JTiJdLCJpYXQiOjE3MzcxMTM5NjAsImV4cCI6MTc2NzExMzk2MH0.xnwSBv3TIugpSnWJU7izOPlBNoXotgoOirW-rfIIlyFNUVOyHpy8bilmWE98n412cKGPmcknWhv85gbZrUUxFg",
									"type": "string"
								}
							]
						},
						"method": "GET",
						"header": [],
						"url": {
							"raw": "http://localhost:8080/rentals?is_active=true",
							"protocol": "http",
							"host": [
								"localhost"
							],
							"port": "8080",
							"path": [
								"rentals"
							],
							"query": [
								{
									"key": "is_active",
									"value": "true"
								}
							]
						}
					},
					"response": []
				},
				{
					"name": "get specific rental",
					"request": {
						"auth": {
							"type": "bearer",
							"bearer": [
								{
									"key": "token",
									"value": "eyJhbGciOiJIUzUxMiJ9.eyJzdWIiOiJ1c2VyQGV4YW1wbGUuY29tIiwicm9sZXMiOlsiVVNFUiJdLCJpYXQiOjE3MzcwNDM0ODAsImV4cCI6MTc2NzA0MzQ4MH0.mIt_9yEz9CN6RHM39vtXplKwVpYShCejIMGOHNkflMQZOppy8cH_4DWMTxbuq02mqRBtnFhzbZlI-vKqb8gBCQ",
									"type": "string"
								}
							]
						},
						"method": "GET",
						"header": [],
						"url": {
							"raw": "http://localhost:8080/rentals/1",
							"protocol": "http",
							"host": [
								"localhost"
							],
							"port": "8080",
							"path": [
								"rentals",
								"1"
							]
						}
					},
					"response": []
				},
				{
					"name": "get all user's rentals",
					"request": {
						"auth": {
							"type": "bearer",
							"bearer": [
								{
									"key": "token",
									"value": "eyJhbGciOiJIUzUxMiJ9.eyJzdWIiOiJ1c2VyQGV4YW1wbGUuY29tIiwicm9sZXMiOlsiVVNFUiJdLCJpYXQiOjE3MzcxMTQyMjMsImV4cCI6MTc2NzExNDIyM30.rAAs-CwZfwMCN5r1xWI2lsPMu4ZXjobkud0XA4BQWditk0ZQFzfFpOM08QcNEXAMS4Kh1NEbwEcuyWKVBZVaxA",
									"type": "string"
								}
							]
						},
						"method": "GET",
						"header": [],
						"url": {
							"raw": "http://localhost:8080/rentals?is_active=false&userId=2",
							"protocol": "http",
							"host": [
								"localhost"
							],
							"port": "8080",
							"path": [
								"rentals"
							],
							"query": [
								{
									"key": "is_active",
									"value": "false"
								},
								{
									"key": "userId",
									"value": "2"
								}
							]
						}
					},
					"response": []
				},
				{
					"name": "get all user's active rentals ",
					"request": {
						"auth": {
							"type": "bearer",
							"bearer": [
								{
									"key": "token",
									"value": "eyJhbGciOiJIUzUxMiJ9.eyJzdWIiOiJ1c2VyQGV4YW1wbGUuY29tIiwicm9sZXMiOlsiVVNFUiJdLCJpYXQiOjE3MzcxMTQyMjMsImV4cCI6MTc2NzExNDIyM30.rAAs-CwZfwMCN5r1xWI2lsPMu4ZXjobkud0XA4BQWditk0ZQFzfFpOM08QcNEXAMS4Kh1NEbwEcuyWKVBZVaxA",
									"type": "string"
								}
							]
						},
						"method": "GET",
						"header": [],
						"url": {
							"raw": "http://localhost:8080/rentals?is_active=true&userId=2",
							"protocol": "http",
							"host": [
								"localhost"
							],
							"port": "8080",
							"path": [
								"rentals"
							],
							"query": [
								{
									"key": "is_active",
									"value": "true"
								},
								{
									"key": "userId",
									"value": "2"
								}
							]
						}
					},
					"response": []
				}
			]
		},
		{
			"name": "payment",
			"item": [
				{
					"name": "create payment",
					"request": {
						"auth": {
							"type": "bearer",
							"bearer": [
								{
									"key": "token",
									"value": "eyJhbGciOiJIUzUxMiJ9.eyJzdWIiOiJ1c2VyQGV4YW1wbGUuY29tIiwicm9sZXMiOlsiVVNFUiJdLCJpYXQiOjE3Mzc2NDk0MDAsImV4cCI6MTc2NzY0OTQwMH0.qQAsLYSrDyWK7PqDWjFSfCuL5rMgKZhHvZR5YMXJqlSgYmd-Dxp81FQB4KUVxIK0l2WzB482qpujUVDfYonf3w",
									"type": "string"
								}
							]
						},
						"method": "POST",
						"header": [],
						"body": {
							"mode": "raw",
							"raw": "{\r\n    \"rentalId\":\"1\",\r\n    \"type\":\"FINE\"\r\n}",
							"options": {
								"raw": {
									"language": "json"
								}
							}
						},
						"url": {
							"raw": "http://localhost:8080/payments",
							"protocol": "http",
							"host": [
								"localhost"
							],
							"port": "8080",
							"path": [
								"payments"
							]
						}
					},
					"response": []
				},
				{
					"name": "get my payments",
					"request": {
						"auth": {
							"type": "bearer",
							"bearer": [
								{
									"key": "token",
									"value": "eyJhbGciOiJIUzUxMiJ9.eyJzdWIiOiJ1c2VyQGV4YW1wbGUuY29tIiwicm9sZXMiOlsiVVNFUiJdLCJpYXQiOjE3Mzc1NDQ2NjEsImV4cCI6MTc2NzU0NDY2MX0.7p8RwTbg22L5Tfvn3AyMUjt2k51LcQ9fnLSXMErmJhjFvJFC00UG4uGbfJWABGoZdTgVecMpIb8oyJIE9dzl_w",
									"type": "string"
								}
							]
						},
						"method": "GET",
						"header": [],
						"url": {
							"raw": "http://localhost:8080/payments",
							"protocol": "http",
							"host": [
								"localhost"
							],
							"port": "8080",
							"path": [
								"payments"
							]
						}
					},
					"response": []
				},
				{
					"name": "get user's payments",
					"request": {
						"auth": {
							"type": "bearer",
							"bearer": [
								{
									"key": "token",
									"value": "eyJhbGciOiJIUzUxMiJ9.eyJzdWIiOiJ1c2VyQGV4YW1wbGUuY29tIiwicm9sZXMiOlsiVVNFUiJdLCJpYXQiOjE3Mzc1NDQ2NjEsImV4cCI6MTc2NzU0NDY2MX0.7p8RwTbg22L5Tfvn3AyMUjt2k51LcQ9fnLSXMErmJhjFvJFC00UG4uGbfJWABGoZdTgVecMpIb8oyJIE9dzl_w",
									"type": "string"
								}
							]
						},
						"method": "GET",
						"header": [],
						"url": {
							"raw": "http://localhost:8080/payments?user=2",
							"protocol": "http",
							"host": [
								"localhost"
							],
							"port": "8080",
							"path": [
								"payments"
							],
							"query": [
								{
									"key": "user",
									"value": "2"
								}
							]
						}
					},
					"response": []
				},
				{
					"name": "renew payment",
					"request": {
						"auth": {
							"type": "bearer",
							"bearer": [
								{
									"key": "token",
									"value": "eyJhbGciOiJIUzUxMiJ9.eyJzdWIiOiJ1c2VyQGV4YW1wbGUuY29tIiwicm9sZXMiOlsiVVNFUiJdLCJpYXQiOjE3Mzc2NDk0MDAsImV4cCI6MTc2NzY0OTQwMH0.qQAsLYSrDyWK7PqDWjFSfCuL5rMgKZhHvZR5YMXJqlSgYmd-Dxp81FQB4KUVxIK0l2WzB482qpujUVDfYonf3w",
									"type": "string"
								}
							]
						},
						"method": "POST",
						"header": [],
						"url": {
							"raw": "http://localhost:8080/payments/1",
							"protocol": "http",
							"host": [
								"localhost"
							],
							"port": "8080",
							"path": [
								"payments",
								"1"
							]
						}
					},
					"response": []
				}
			]
		}
	]
}